basinex/__init__.py
basinex/netcdf.py
basinex/main.py
basinex/gauges.py
basinex/extractor.cpython-37m-x86_64-linux-gnu.so
basinex/wrapper.py
basinex/_version.py
basinex/geoarray/gdalspatial.py
basinex/geoarray/utils.py
basinex/geoarray/__init__.py
basinex/geoarray/core.py
basinex/geoarray/gdalfuncs.py
basinex/geoarray/geotrans.py
basinex/geoarray/spatial.py
basinex/geoarray/gdalio.py
basinex/geoarray/wrapper.py
basinex/netcdf4/utils.py
basinex/netcdf4/netcdf4.py
basinex/netcdf4/__init__.py
basinex-0.2.0.dist-info/entry_points.txt
basinex-0.2.0.dist-info/WHEEL
basinex-0.2.0.dist-info/METADATA
basinex-0.2.0.dist-info/LICENSE
basinex-0.2.0.dist-info/top_level.txt
basinex-0.2.0.dist-info/RECORD
