Metadata-Version: 2.1
Name: basinex
Version: 0.2.0
Summary: A basin extractor.
Home-page: https://github.com/mhm-ufz/basinex
Author: mHM Developers
Author-email: mhm-developers@ufz.de
Maintainer: Sebastian Müller
Maintainer-email: sebastian.mueller@ufz.de
License: LGPL-3.0
Project-URL: Documentation, https://basinex.readthedocs.io
Project-URL: Source, https://github.com/mhm-ufz/basinex
Project-URL: Tracker, https://github.com/mhm-ufz/basinex/issues
Project-URL: Changelog, https://github.com/mhm-ufz/basinex/blob/main/CHANGELOG.md
Platform: any
Classifier: Development Status :: 4 - Beta
Classifier: Intended Audience :: Developers
Classifier: Intended Audience :: End Users/Desktop
Classifier: Intended Audience :: Science/Research
Classifier: Intended Audience :: Education
Classifier: License :: OSI Approved :: GNU Lesser General Public License v3 (LGPLv3)
Classifier: Natural Language :: English
Classifier: Operating System :: Unix
Classifier: Operating System :: Microsoft
Classifier: Operating System :: MacOS
Classifier: Programming Language :: Python
Classifier: Programming Language :: Python :: 3
Classifier: Programming Language :: Python :: 3 :: Only
Classifier: Programming Language :: Python :: 3.6
Classifier: Programming Language :: Python :: 3.7
Classifier: Programming Language :: Python :: 3.8
Classifier: Programming Language :: Python :: 3.9
Classifier: Programming Language :: Python :: 3.10
Classifier: Topic :: Scientific/Engineering
Classifier: Topic :: Scientific/Engineering :: GIS
Classifier: Topic :: Scientific/Engineering :: Hydrology
Classifier: Topic :: Scientific/Engineering :: Mathematics
Classifier: Topic :: Scientific/Engineering :: Physics
Classifier: Topic :: Utilities
Requires-Python: >=3.6
License-File: LICENSE
Requires-Dist: numpy (>=1.14.5)
Requires-Dist: pyyaml
Requires-Dist: gdal
Requires-Dist: netcdf4 (<1.6)
Provides-Extra: doc
Requires-Dist: m2r2 (>=0.2.8) ; extra == 'doc'
Requires-Dist: sphinx (>=4) ; extra == 'doc'
Requires-Dist: sphinx-rtd-theme (>=1) ; extra == 'doc'
Provides-Extra: test
Requires-Dist: pytest-cov (>=3) ; extra == 'test'
